{"nasconv_0": "1", "nasconv_0_act": "1", "nasconv_1": "1", "nasconv_1_act": "2", "c3_2": "0", "nasconv_2-1": "1", "nasconv_2-1_act": "1", "nasconv_2-2": "1", "nasconv_2-2_act": "2", "model_1": 1.5, "model_2": 1, "model_3": 1.5, "model_4": 1, "nasconv_3": "0", "nasconv_3_act": "2", "c3_4": "2", "nasconv_4-1": "0", "nasconv_4-1_act": "0", "nasconv_4-2": "1", "nasconv_4-2_act": "1", "model_5": 1.5, "model_6": 2, "model_7": 1, "model_8": 2, "model_9": 2, "model_10": 2, "model_11": 1, "model_12": 1.5, "nasconv_5": "0", "nasconv_5_act": "2", "c3_6": "1", "nasconv_6-1": "0", "nasconv_6-1_act": "2", "nasconv_6-2": "1", "nasconv_6-2_act": "2", "model_13": 2, "model_14": 2, "model_15": 1.5, "model_16": 1.5, "model_17": 2, "model_18": 1.5, "model_19": 2, "model_20": 2, "model_21": 2, "model_22": 1.5, "model_23": 1.5, "model_24": 1.5, "nasconv_7": "1", "nasconv_7_act": "2", "c3_8": "0", "nasconv_8-1": "1", "nasconv_8-1_act": "2", "nasconv_8-2": "1", "nasconv_8-2_act": "2", "model_25": 2, "model_26": 2, "model_27": 2, "model_28": 1}